py4etrics/__init__.py
py4etrics/base_for_models.py
py4etrics/heckit.py
py4etrics/hetero_test.py
py4etrics/tobit.py
py4etrics/truncreg.py
py4etrics-0.1.9.dist-info/LICENSE
py4etrics-0.1.9.dist-info/METADATA
py4etrics-0.1.9.dist-info/WHEEL
py4etrics-0.1.9.dist-info/top_level.txt
py4etrics-0.1.9.dist-info/RECORD
