Metadata-Version: 2.1
Name: py4etrics
Version: 0.1.9
Summary: A package for py4etrics.github.io
Home-page: https://github.com/Py4Etrics/py4etrics
Author: Tetsu HARUYAMA
Author-email: haruyama@econ.kobe-u.ac.jp
License: MIT
Keywords: Truncated Regression,Tobit Model,Heckit Model
Classifier: Intended Audience :: Education
Classifier: Intended Audience :: Science/Research
Classifier: License :: OSI Approved :: MIT License
Classifier: Operating System :: OS Independent
Classifier: Programming Language :: Python
License-File: LICENSE
